{
  "install_modes": {
    "global": [
      {
        "name": "Winget",
        "type": "winget",
        "package": "chess-tui"
      },
      {
        "name": "Chocolatey",
        "type": "choco",
        "package": "chess-tui"
      }
    ],
    "user": [
      {
        "name": "Winget",
        "type": "winget",
        "package": "chess-tui"
      },
      {
        "name": "Chocolatey",
        "type": "choco",
        "package": "chess-tui"
      }
    ],
    "shim": [
      {
        "name": "Winget",
        "type": "winget",
        "package": "chess-tui"
      },
      {
        "name": "Chocolatey",
        "type": "choco",
        "package": "chess-tui"
      }
    ]
  }
}